{
  "start": {
    "result": "ok",
    "detail": "pipeline started"
  },
  "research": {
    "result": "ok",
    "detail": ""
  },
  "ideas": {
    "result": "ok",
    "detail": "6 ideas"
  },
  "script": {
    "result": "ok",
    "detail": "Loving in Silence"
  },
  "audio": {
    "result": "ok",
    "detail": "/home/runner/work/quietlyy/quietlyy/scripts/../output/voiceover.mp3"
  },
  "images": {
    "result": "ok",
    "detail": "5 panels"
  },
  "music": {
    "result": "ok",
    "detail": "/home/runner/work/quietlyy/quietlyy/scripts/../output/background_music.mp3 [gallery_library]"
  },
  "video": {
    "result": "ok",
    "detail": "/home/runner/work/quietlyy/quietlyy/scripts/../output/quietlyy_video.mp4"
  },
  "quality_gate": {
    "result": "fail",
    "detail": "Audio too small (97344 bytes)"
  }
}